llm_processor/__init__.py
llm_processor/cli.py
llm_processor/processor.py
llm_data_processor-0.1.2.dist-info/METADATA
llm_data_processor-0.1.2.dist-info/WHEEL
llm_data_processor-0.1.2.dist-info/entry_points.txt
llm_data_processor-0.1.2.dist-info/top_level.txt
llm_data_processor-0.1.2.dist-info/RECORD
