Metadata-Version: 2.4
Name: llm-data-processor
Version: 0.1.2
Summary: A processor for LLM tasks
Author-email: DG chen <94503663@qq.com>
Project-URL: Homepage, https://github.com/yourusername/llm-processor
Project-URL: Bug Tracker, https://github.com/yourusername/llm-processor/issues
Classifier: Development Status :: 3 - Alpha
Classifier: Intended Audience :: Developers
Classifier: License :: OSI Approved :: MIT License
Classifier: Programming Language :: Python :: 3
Classifier: Programming Language :: Python :: 3.8
Classifier: Programming Language :: Python :: 3.9
Classifier: Programming Language :: Python :: 3.10
Requires-Python: >=3.8
Requires-Dist: pyyaml
Requires-Dist: requests
Requires-Dist: asyncio
Requires-Dist: aiohttp
Requires-Dist: asyncpg
Requires-Dist: openai
